nso_restconf/__init__.py
nso_restconf/restconf.py
nso_restconf-2.0.2.dist-info/LICENSE
nso_restconf-2.0.2.dist-info/METADATA
nso_restconf-2.0.2.dist-info/WHEEL
nso_restconf-2.0.2.dist-info/top_level.txt
nso_restconf-2.0.2.dist-info/RECORD
