Metadata-Version: 2.1
Name: nso-restconf
Version: 2.0.2
Summary: A wrapper for managing the API of NSO
Home-page: https://github.com/rtrjl/nso_restconf
Author: Rodolphe Trujillo
Author-email: rodtruji@cisco.com
License: Cisco Sample Code License, Version 1.1
Platform: UNKNOWN
Classifier: Topic :: System :: Networking
License-File: LICENSE
Requires-Dist: requests
